yt_playlist_dl/__init__.py
yt_playlist_dl/command_line.py
yt_playlist_dl-0.2.0.dist-info/LICENSE
yt_playlist_dl-0.2.0.dist-info/METADATA
yt_playlist_dl-0.2.0.dist-info/WHEEL
yt_playlist_dl-0.2.0.dist-info/entry_points.txt
yt_playlist_dl-0.2.0.dist-info/top_level.txt
yt_playlist_dl-0.2.0.dist-info/RECORD
