Metadata-Version: 2.1
Name: yt-playlist-dl
Version: 0.2.0
Summary: A tool to download (and keep up-to-date) playlists from youtube.
Home-page: https://github.com/tusharsadhwani/yt_playlist_dl
Author: Tushar Sadhwani
Author-email: tushar.sadhwani000@gmail.com
License: UNKNOWN
Platform: UNKNOWN
Classifier: Programming Language :: Python :: 3
Classifier: License :: OSI Approved :: MIT License
Classifier: Operating System :: OS Independent
Requires-Python: >=3.6
Requires-Dist: youtube-dl
